LICENSE
MANIFEST.in
README.md
README.rst
setup.cfg
setup.py
bpmn_python/__init__.py
bpmn_python/bpmn_diagram_exception.py
bpmn_python/bpmn_diagram_export.py
bpmn_python/bpmn_diagram_import.py
bpmn_python/bpmn_diagram_layouter.py
bpmn_python/bpmn_diagram_metrics.py
bpmn_python/bpmn_diagram_rep.py
bpmn_python/bpmn_diagram_visualizer.py
bpmn_python/bpmn_import_utils.py
bpmn_python/bpmn_process_csv_export.py
bpmn_python/bpmn_process_csv_import.py
bpmn_python/bpmn_python_consts.py
bpmn_python/diagram_layout_metrics.py
bpmn_python/grid_cell_class.py
bpmn_python.egg-info/PKG-INFO
bpmn_python.egg-info/SOURCES.txt
bpmn_python.egg-info/dependency_links.txt
bpmn_python.egg-info/requires.txt
bpmn_python.egg-info/top_level.txt
bpmn_python/graph/__init__.py
bpmn_python/graph/classes/__init__.py
bpmn_python/graph/classes/base_element_type.py
bpmn_python/graph/classes/condition_expression_type.py
bpmn_python/graph/classes/flow_element_type.py
bpmn_python/graph/classes/flow_node_type.py
bpmn_python/graph/classes/lane_set_type.py
bpmn_python/graph/classes/lane_type.py
bpmn_python/graph/classes/message_flow_type.py
bpmn_python/graph/classes/participant_type.py
bpmn_python/graph/classes/sequence_flow_type.py
bpmn_python/graph/classes/activities/__init__.py
bpmn_python/graph/classes/activities/activity_type.py
bpmn_python/graph/classes/activities/subprocess_type.py
bpmn_python/graph/classes/activities/task_type.py
bpmn_python/graph/classes/events/__init__.py
bpmn_python/graph/classes/events/catch_event_type.py
bpmn_python/graph/classes/events/end_event_type.py
bpmn_python/graph/classes/events/event_type.py
bpmn_python/graph/classes/events/intermediate_catch_event_type.py
bpmn_python/graph/classes/events/intermediate_throw_event_type.py
bpmn_python/graph/classes/events/start_event_type.py
bpmn_python/graph/classes/events/throw_event_type.py
bpmn_python/graph/classes/gateways/__init__.py
bpmn_python/graph/classes/gateways/exclusive_gateway_type.py
bpmn_python/graph/classes/gateways/gateway_type.py
bpmn_python/graph/classes/gateways/inclusive_gateway_type.py
bpmn_python/graph/classes/gateways/parallel_gateway_type.py
