Metadata-Version: 1.1
Name: bpmn-python
Version: 0.0.14
Summary: Python library that allows to import/export BPMN diagram (as an XML file) and provides a simple visualization capabilities.
Home-page: https://github.com/KrzyHonk/bpmn-python
Author: Izbela Smietana, Krzysztof Honkisz
Author-email: UNKNOWN
License: GNU GENERAL PUBLIC LICENSE
Download-URL: https://github.com/KrzyHonk/bpmn-python/tarball/0.0.14
Keywords: bpmn,xml
Platform: UNKNOWN
